[
    {
        "data": [
            {
                "text": "Hola estoy muy ",
                "userDefined": false
            },
            {
                "text": "sola",
                "meta": "@estado",
                "alias": "estado",
                "userDefined": false
            },
            {
                "text": " necesito de tus consejos y que me hagas compañía😢😢😢",
                "userDefined": false
            }
        ],
        "isTemplate": false,
        "count": 0,
        "lang": "es",
        "updated": 0
    },
    {
        "data": [
            {
                "text": "Hola, he estado un poco ",
                "userDefined": false
            },
            {
                "text": "ocupado",
                "meta": "@estado",
                "alias": "estado",
                "userDefined": false
            },
            {
                "text": ", lo siento, intentaré estar más en adelante en lo posible",
                "userDefined": false
            }
        ],
        "isTemplate": false,
        "count": 0,
        "lang": "es",
        "updated": 0
    },
    {
        "data": [
            {
                "text": "Bien, ",
                "userDefined": false
            },
            {
                "text": "muy bien",
                "meta": "@estado",
                "alias": "estado",
                "userDefined": false
            },
            {
                "text": ", viendo una serie.",
                "userDefined": false
            }
        ],
        "isTemplate": false,
        "count": 0,
        "lang": "es",
        "updated": 0
    },
    {
        "data": [
            {
                "text": "Hola! Todo ",
                "userDefined": false
            },
            {
                "text": "bien",
                "meta": "@estado",
                "alias": "estado",
                "userDefined": false
            },
            {
                "text": ", muchas gracias, ☺️",
                "userDefined": false
            }
        ],
        "isTemplate": false,
        "count": 0,
        "lang": "es",
        "updated": 0
    },
    {
        "data": [
            {
                "text": "Estoy muy ",
                "userDefined": false
            },
            {
                "text": "bien",
                "meta": "@estado",
                "alias": "estado",
                "userDefined": false
            }
        ],
        "isTemplate": false,
        "count": 0,
        "lang": "es",
        "updated": 0
    },
    {
        "data": [
            {
                "text": "Anoche no dormí bien",
                "userDefined": false
            },
            {
                "text": "sueño",
                "meta": "@estado",
                "alias": "estado",
                "userDefined": false
            }
        ],
        "isTemplate": false,
        "count": 0,
        "lang": "es",
        "updated": 0
    },
    {
        "data": [
            {
                "text": "Estoy ",
                "userDefined": false
            },
            {
                "text": "disgustada",
                "meta": "@estado",
                "alias": "estado",
                "userDefined": false
            },
            {
                "text": " mi amiga tiene un problema y no s como ayudarla",
                "userDefined": false
            }
        ],
        "isTemplate": false,
        "count": 0,
        "lang": "es",
        "updated": 0
    },
    {
        "data": [
            {
                "text": "Estoy ",
                "userDefined": false
            },
            {
                "text": "bien",
                "meta": "@estado",
                "alias": "estado",
                "userDefined": false
            }
        ],
        "isTemplate": false,
        "count": 0,
        "lang": "es",
        "updated": 0
    },
    {
        "data": [
            {
                "text": "Mañana celebramos el Día de la madre comemos en el centro comercial pero no estamos todos como me gustaría otro año será",
                "userDefined": false
            },
            {
                "text": "tristeza",
                "meta": "@estado",
                "alias": "estado",
                "userDefined": false
            }
        ],
        "isTemplate": false,
        "count": 0,
        "lang": "es",
        "updated": 0
    },
    {
        "data": [
            {
                "text": "Todo ",
                "userDefined": false
            },
            {
                "text": "bien",
                "meta": "@estado",
                "alias": "estado",
                "userDefined": false
            },
            {
                "text": ". Muchas gracias",
                "userDefined": false
            }
        ],
        "isTemplate": false,
        "count": 0,
        "lang": "es",
        "updated": 0
    },
    {
        "data": [
            {
                "text": "Está todo ",
                "userDefined": false
            },
            {
                "text": "bien",
                "meta": "@estado",
                "alias": "estado",
                "userDefined": false
            },
            {
                "text": " 👍🏻",
                "userDefined": false
            }
        ],
        "isTemplate": false,
        "count": 0,
        "lang": "es",
        "updated": 0
    },
    {
        "data": [
            {
                "text": "Me acaban de llamar por teléfono me han dado muy buenas noticias acaban de solucionarme un problema que hacía meses tenía",
                "userDefined": false
            },
            {
                "text": "felicidad",
                "meta": "@estado",
                "alias": "estado",
                "userDefined": false
            }
        ],
        "isTemplate": false,
        "count": 0,
        "lang": "es",
        "updated": 0
    },
    {
        "data": [
            {
                "text": "Hola ",
                "userDefined": false
            },
            {
                "text": "muy bien",
                "meta": "@estado",
                "alias": "estado",
                "userDefined": false
            },
            {
                "text": " en Torrevieja cerca del mar",
                "userDefined": false
            }
        ],
        "isTemplate": false,
        "count": 0,
        "lang": "es",
        "updated": 0
    },
    {
        "data": [
            {
                "text": "Y estoy ",
                "userDefined": false
            },
            {
                "text": "cansada",
                "meta": "@estado",
                "alias": "estado",
                "userDefined": false
            }
        ],
        "isTemplate": false,
        "count": 0,
        "lang": "es",
        "updated": 0
    },
    {
        "data": [
            {
                "text": "Me siento ",
                "userDefined": false
            },
            {
                "text": "muy contenta",
                "meta": "@estado",
                "alias": "estado",
                "userDefined": false
            },
            {
                "text": " de tener un amigo",
                "userDefined": false
            }
        ],
        "isTemplate": false,
        "count": 0,
        "lang": "es",
        "updated": 0
    },
    {
        "data": [
            {
                "text": "Bien... aquí pasando el tiempo",
                "userDefined": false
            },
            {
                "text": "bien",
                "meta": "@estado",
                "alias": "estado",
                "userDefined": false
            }
        ],
        "isTemplate": false,
        "count": 0,
        "lang": "es",
        "updated": 0
    },
    {
        "data": [
            {
                "text": "Hola es que me han dado puntos y estoy muy ",
                "userDefined": false
            },
            {
                "text": "molests",
                "meta": "@estado",
                "alias": "estado",
                "userDefined": false
            }
        ],
        "isTemplate": false,
        "count": 0,
        "lang": "es",
        "updated": 0
    },
    {
        "data": [
            {
                "text": "Que estoy ",
                "userDefined": false
            },
            {
                "text": "cansada",
                "meta": "@estado",
                "alias": "estado",
                "userDefined": false
            }
        ],
        "isTemplate": false,
        "count": 0,
        "lang": "es",
        "updated": 0
    },
    {
        "data": [
            {
                "text": "Hola estoy ",
                "userDefined": false
            },
            {
                "text": "muy contenta",
                "meta": "@estado",
                "alias": "estado",
                "userDefined": false
            },
            {
                "text": " hemos pagado menos feliz este mes",
                "userDefined": false
            }
        ],
        "isTemplate": false,
        "count": 0,
        "lang": "es",
        "updated": 0
    }
]